readunwise/__init__.py
readunwise/cli.py
readunwise/clippings.py
readunwise/discord_client.py
readunwise/highlight.py
readunwise/random_util.py
readunwise/readwise_client.py
readunwise/test/test_highlight.py
readunwise-0.1.5.dist-info/licenses/LICENSE
readunwise-0.1.5.dist-info/METADATA
readunwise-0.1.5.dist-info/WHEEL
readunwise-0.1.5.dist-info/entry_points.txt
readunwise-0.1.5.dist-info/top_level.txt
readunwise-0.1.5.dist-info/RECORD
