Metadata-Version: 2.4
Name: readunwise
Version: 0.1.5
Summary: CLI for managing Amazon Kindle highlights
Author-email: Fred Glass <fred@fred.glass>
License-File: LICENSE
Requires-Dist: click==8.1.3
Requires-Dist: discord==2.1.0
Requires-Dist: rich==13.3.1
Requires-Dist: requests>=2.32.4
Dynamic: license-file
